[
    {
        "playlist_id": 72,
        "source": "youtube",
        "video_id": "l1ZKYvXBgx4",
        "song_title": "On My Way",
        "thumbnails": {
            "default": {
                "url": "https://i.ytimg.com/vi/l1ZKYvXBgx4/default.jpg",
                "width": 120,
                "height": 90
            },
            "medium": {
                "url": "https://i.ytimg.com/vi/l1ZKYvXBgx4/mqdefault.jpg",
                "width": 320,
                "height": 180
            },
            "high": {
                "url": "https://i.ytimg.com/vi/l1ZKYvXBgx4/hqdefault.jpg",
                "width": 480,
                "height": 360
            }
        },
        "song_lang": "",
        "vocal": "U",
        "artist": "Alan Walker,Sabrina Carpenter,Farruko",
        "tag": ""
    },
    {
        "playlist_id": 72,
        "source": "youtube",
        "video_id": "G5Mv2iV0wkU",
        "song_title": "Kills You Slowly (Explicit)",
        "thumbnails": {
            "default": {
                "url": "https://i.ytimg.com/vi/G5Mv2iV0wkU/default.jpg",
                "width": 120,
                "height": 90
            },
            "medium": {
                "url": "https://i.ytimg.com/vi/G5Mv2iV0wkU/mqdefault.jpg",
                "width": 320,
                "height": 180
            },
            "high": {
                "url": "https://i.ytimg.com/vi/G5Mv2iV0wkU/hqdefault.jpg",
                "width": 480,
                "height": 360
            }
        },
        "song_lang": "",
        "vocal": "U",
        "artist": "The Chainsmokers",
        "tag": ""
    },
    {
        "playlist_id": 72,
        "source": "youtube",
        "video_id": "C4MjQwrePO0",
        "song_title": "Better Man",
        "thumbnails": {
            "default": {
                "url": "https://i.ytimg.com/vi/C4MjQwrePO0/default.jpg",
                "width": 120,
                "height": 90
            },
            "medium": {
                "url": "https://i.ytimg.com/vi/C4MjQwrePO0/mqdefault.jpg",
                "width": 320,
                "height": 180
            },
            "high": {
                "url": "https://i.ytimg.com/vi/C4MjQwrePO0/hqdefault.jpg",
                "width": 480,
                "height": 360
            }
        },
        "song_lang": "",
        "vocal": "U",
        "artist": "Westlife",
        "tag": ""
    },
    {
        "playlist_id": 72,
        "source": "youtube",
        "video_id": "pRLR3DtbrAw",
        "song_title": "MONOPOLY (Explicit)",
        "thumbnails": {
            "default": {
                "url": "https://i.ytimg.com/vi/pRLR3DtbrAw/default.jpg",
                "width": 120,
                "height": 90
            },
            "medium": {
                "url": "https://i.ytimg.com/vi/pRLR3DtbrAw/mqdefault.jpg",
                "width": 320,
                "height": 180
            },
            "high": {
                "url": "https://i.ytimg.com/vi/pRLR3DtbrAw/hqdefault.jpg",
                "width": 480,
                "height": 360
            }
        },
        "song_lang": "",
        "vocal": "U",
        "artist": "Ariana Grande,Victoria Monet",
        "tag": ""
    },
    {
        "playlist_id": 72,
        "source": "youtube",
        "video_id": "Ox-1fX6acM0",
        "song_title": "Crying Over You ◐ (feat. RM & Bibi Zhou)",
        "thumbnails": {
            "default": {
                "url": "https://i.ytimg.com/vi/Ox-1fX6acM0/default.jpg",
                "width": 120,
                "height": 90
            },
            "medium": {
                "url": "https://i.ytimg.com/vi/Ox-1fX6acM0/mqdefault.jpg",
                "width": 320,
                "height": 180
            },
            "high": {
                "url": "https://i.ytimg.com/vi/Ox-1fX6acM0/hqdefault.jpg",
                "width": 480,
                "height": 360
            }
        },
        "song_lang": "",
        "vocal": "U",
        "artist": "Honne,RM ,周笔畅",
        "tag": ""
    },
    {
        "playlist_id": 72,
        "source": "youtube",
        "video_id": "9-klJ6EQfe8",
        "song_title": "Mistaken",
        "thumbnails": {
            "default": {
                "url": "https://i.ytimg.com/vi/9-klJ6EQfe8/default.jpg",
                "width": 120,
                "height": 90
            },
            "medium": {
                "url": "https://i.ytimg.com/vi/9-klJ6EQfe8/mqdefault.jpg",
                "width": 320,
                "height": 180
            },
            "high": {
                "url": "https://i.ytimg.com/vi/9-klJ6EQfe8/hqdefault.jpg",
                "width": 480,
                "height": 360
            }
        },
        "song_lang": "",
        "vocal": "U",
        "artist": "Martin Garrix,Matisse , Sadko,Alex Aris",
        "tag": ""
    },
    {
        "playlist_id": 72,
        "source": "youtube",
        "video_id": "a6e65r73ld4",
        "song_title": "bad guy",
        "thumbnails": {
            "default": {
                "url": "https://i.ytimg.com/vi/a6e65r73ld4/default.jpg",
                "width": 120,
                "height": 90
            },
            "medium": {
                "url": "https://i.ytimg.com/vi/a6e65r73ld4/mqdefault.jpg",
                "width": 320,
                "height": 180
            },
            "high": {
                "url": "https://i.ytimg.com/vi/a6e65r73ld4/hqdefault.jpg",
                "width": 480,
                "height": 360
            }
        },
        "song_lang": "",
        "vocal": "U",
        "artist": "Billie Eilish",
        "tag": ""
    },
    {
        "playlist_id": 72,
        "source": "youtube",
        "video_id": "6l8gyacUq4w",
        "song_title": "Broken & Beautiful (from the movie UGLYDOLLS)",
        "thumbnails": {
            "default": {
                "url": "https://i.ytimg.com/vi/6l8gyacUq4w/default.jpg",
                "width": 120,
                "height": 90
            },
            "medium": {
                "url": "https://i.ytimg.com/vi/6l8gyacUq4w/mqdefault.jpg",
                "width": 320,
                "height": 180
            },
            "high": {
                "url": "https://i.ytimg.com/vi/6l8gyacUq4w/hqdefault.jpg",
                "width": 480,
                "height": 360
            }
        },
        "song_lang": "",
        "vocal": "U",
        "artist": "Kelly Clarkson",
        "tag": ""
    },
    {
        "playlist_id": 72,
        "source": "youtube",
        "video_id": "-A_wgbkY-Bg",
        "song_title": "Low Mist (Day 1)",
        "thumbnails": {
            "default": {
                "url": "https://i.ytimg.com/vi/-A_wgbkY-Bg/default.jpg",
                "width": 120,
                "height": 90
            },
            "medium": {
                "url": "https://i.ytimg.com/vi/-A_wgbkY-Bg/mqdefault.jpg",
                "width": 320,
                "height": 180
            },
            "high": {
                "url": "https://i.ytimg.com/vi/-A_wgbkY-Bg/hqdefault.jpg",
                "width": 480,
                "height": 360
            }
        },
        "song_lang": "",
        "vocal": "U",
        "artist": "Ludovico Einaudi,Federico Mecozzi,Redi Hasa",
        "tag": ""
    },
    {
        "playlist_id": 72,
        "source": "youtube",
        "video_id": "4XWcvRpp0eg",
        "song_title": "Mi Persona Favorita",
        "thumbnails": {
            "default": {
                "url": "https://i.ytimg.com/vi/4XWcvRpp0eg/default.jpg",
                "width": 120,
                "height": 90
            },
            "medium": {
                "url": "https://i.ytimg.com/vi/4XWcvRpp0eg/mqdefault.jpg",
                "width": 320,
                "height": 180
            },
            "high": {
                "url": "https://i.ytimg.com/vi/4XWcvRpp0eg/hqdefault.jpg",
                "width": 480,
                "height": 360
            }
        },
        "song_lang": "",
        "vocal": "U",
        "artist": "Alejandro Sanz,Camila Cabello",
        "tag": ""
    },
    {
        "playlist_id": 72,
        "source": "youtube",
        "video_id": "lhijsiOJikw",
        "song_title": "Live It Up",
        "thumbnails": {
            "default": {
                "url": "https://i.ytimg.com/vi/lhijsiOJikw/default.jpg",
                "width": 120,
                "height": 90
            },
            "medium": {
                "url": "https://i.ytimg.com/vi/lhijsiOJikw/mqdefault.jpg",
                "width": 320,
                "height": 180
            },
            "high": {
                "url": "https://i.ytimg.com/vi/lhijsiOJikw/hqdefault.jpg",
                "width": 480,
                "height": 360
            }
        },
        "song_lang": "",
        "vocal": "U",
        "artist": "Kristian Kostov,陈梓童",
        "tag": ""
    },
    {
        "playlist_id": 72,
        "source": "youtube",
        "video_id": "djw8cooZ4ds",
        "song_title": "Here With Me",
        "thumbnails": {
            "default": {
                "url": "https://i.ytimg.com/vi/djw8cooZ4ds/default.jpg",
                "width": 120,
                "height": 90
            },
            "medium": {
                "url": "https://i.ytimg.com/vi/djw8cooZ4ds/mqdefault.jpg",
                "width": 320,
                "height": 180
            },
            "high": {
                "url": "https://i.ytimg.com/vi/djw8cooZ4ds/hqdefault.jpg",
                "width": 480,
                "height": 360
            }
        },
        "song_lang": "",
        "vocal": "U",
        "artist": "Marshmello,CHVRCHES",
        "tag": ""
    },
    {
        "playlist_id": 72,
        "source": "youtube",
        "video_id": "q_5KPQR1Lrs",
        "song_title": "Walk Away",
        "thumbnails": {
            "default": {
                "url": "https://i.ytimg.com/vi/q_5KPQR1Lrs/default.jpg",
                "width": 120,
                "height": 90
            },
            "medium": {
                "url": "https://i.ytimg.com/vi/q_5KPQR1Lrs/mqdefault.jpg",
                "width": 320,
                "height": 180
            },
            "high": {
                "url": "https://i.ytimg.com/vi/q_5KPQR1Lrs/hqdefault.jpg",
                "width": 480,
                "height": 360
            }
        },
        "song_lang": "",
        "vocal": "U",
        "artist": "Alle Farben,James Blunt",
        "tag": ""
    },
    {
        "playlist_id": 72,
        "source": "youtube",
        "video_id": "Hz0K7VoAIts",
        "song_title": "Hustle (Explicit)",
        "thumbnails": {
            "default": {
                "url": "https://i.ytimg.com/vi/Hz0K7VoAIts/default.jpg",
                "width": 120,
                "height": 90
            },
            "medium": {
                "url": "https://i.ytimg.com/vi/Hz0K7VoAIts/mqdefault.jpg",
                "width": 320,
                "height": 180
            },
            "high": {
                "url": "https://i.ytimg.com/vi/Hz0K7VoAIts/hqdefault.jpg",
                "width": 480,
                "height": 360
            }
        },
        "song_lang": "",
        "vocal": "U",
        "artist": "P!NK",
        "tag": ""
    },
    {
        "playlist_id": 72,
        "source": "youtube",
        "video_id": "H1GnanQW67E",
        "song_title": "Who Do You Love (R3HAB Remix|Explicit)",
        "thumbnails": {
            "default": {
                "url": "https://i.ytimg.com/vi/H1GnanQW67E/default.jpg",
                "width": 120,
                "height": 90
            },
            "medium": {
                "url": "https://i.ytimg.com/vi/H1GnanQW67E/mqdefault.jpg",
                "width": 320,
                "height": 180
            },
            "high": {
                "url": "https://i.ytimg.com/vi/H1GnanQW67E/hqdefault.jpg",
                "width": 480,
                "height": 360
            }
        },
        "song_lang": "",
        "vocal": "U",
        "artist": "The Chainsmokers,5 Seconds Of Summer,R3hab",
        "tag": ""
    },
    {
        "playlist_id": 72,
        "source": "youtube",
        "video_id": "IOzAmILqFkI",
        "song_title": "wish you were gay",
        "thumbnails": {
            "default": {
                "url": "https://i.ytimg.com/vi/IOzAmILqFkI/default.jpg",
                "width": 120,
                "height": 90
            },
            "medium": {
                "url": "https://i.ytimg.com/vi/IOzAmILqFkI/mqdefault.jpg",
                "width": 320,
                "height": 180
            },
            "high": {
                "url": "https://i.ytimg.com/vi/IOzAmILqFkI/hqdefault.jpg",
                "width": 480,
                "height": 360
            }
        },
        "song_lang": "",
        "vocal": "U",
        "artist": "Billie Eilish",
        "tag": ""
    },
    {
        "playlist_id": 72,
        "source": "youtube",
        "video_id": "em0wtOtSbyY",
        "song_title": "Don't Worry Bout Me",
        "thumbnails": {
            "default": {
                "url": "https://i.ytimg.com/vi/em0wtOtSbyY/default.jpg",
                "width": 120,
                "height": 90
            },
            "medium": {
                "url": "https://i.ytimg.com/vi/em0wtOtSbyY/mqdefault.jpg",
                "width": 320,
                "height": 180
            },
            "high": {
                "url": "https://i.ytimg.com/vi/em0wtOtSbyY/hqdefault.jpg",
                "width": 480,
                "height": 360
            }
        },
        "song_lang": "",
        "vocal": "U",
        "artist": "Zara Larsson",
        "tag": ""
    },
    {
        "playlist_id": 72,
        "source": "youtube",
        "video_id": "xZCLLVYq3O8",
        "song_title": "Sucker",
        "thumbnails": {
            "default": {
                "url": "https://i.ytimg.com/vi/xZCLLVYq3O8/default.jpg",
                "width": 120,
                "height": 90
            },
            "medium": {
                "url": "https://i.ytimg.com/vi/xZCLLVYq3O8/mqdefault.jpg",
                "width": 320,
                "height": 180
            },
            "high": {
                "url": "https://i.ytimg.com/vi/xZCLLVYq3O8/hqdefault.jpg",
                "width": 480,
                "height": 360
            }
        },
        "song_lang": "",
        "vocal": "U",
        "artist": "Jonas Brothers",
        "tag": ""
    },
    {
        "playlist_id": 72,
        "source": "youtube",
        "video_id": "1lLSm-A2ar8",
        "song_title": "Self",
        "thumbnails": {
            "default": {
                "url": "https://i.ytimg.com/vi/1lLSm-A2ar8/default.jpg",
                "width": 120,
                "height": 90
            },
            "medium": {
                "url": "https://i.ytimg.com/vi/1lLSm-A2ar8/mqdefault.jpg",
                "width": 320,
                "height": 180
            },
            "high": {
                "url": "https://i.ytimg.com/vi/1lLSm-A2ar8/hqdefault.jpg",
                "width": 480,
                "height": 360
            }
        },
        "song_lang": "",
        "vocal": "U",
        "artist": "Khalid",
        "tag": ""
    },
    {
        "playlist_id": 72,
        "source": "youtube",
        "video_id": "xdRzsVISVQk",
        "song_title": "Are You Lonely",
        "thumbnails": {
            "default": {
                "url": "https://i.ytimg.com/vi/xdRzsVISVQk/default.jpg",
                "width": 120,
                "height": 90
            },
            "medium": {
                "url": "https://i.ytimg.com/vi/xdRzsVISVQk/mqdefault.jpg",
                "width": 320,
                "height": 180
            },
            "high": {
                "url": "https://i.ytimg.com/vi/xdRzsVISVQk/hqdefault.jpg",
                "width": 480,
                "height": 360
            }
        },
        "song_lang": "",
        "vocal": "U",
        "artist": "Steve Aoki,Alan Walker",
        "tag": ""
    },
    {
        "playlist_id": 72,
        "source": "youtube",
        "video_id": "75fEhQlc9h4",
        "song_title": "I Don't Belong In This Club",
        "thumbnails": {
            "default": {
                "url": "https://i.ytimg.com/vi/75fEhQlc9h4/default.jpg",
                "width": 120,
                "height": 90
            },
            "medium": {
                "url": "https://i.ytimg.com/vi/75fEhQlc9h4/mqdefault.jpg",
                "width": 320,
                "height": 180
            },
            "high": {
                "url": "https://i.ytimg.com/vi/75fEhQlc9h4/hqdefault.jpg",
                "width": 480,
                "height": 360
            }
        },
        "song_lang": "",
        "vocal": "U",
        "artist": "Why Don't We,Macklemore",
        "tag": ""
    },
    {
        "playlist_id": 72,
        "source": "youtube",
        "video_id": "T7IXKQzmpK4",
        "song_title": "Play It Cool",
        "thumbnails": {
            "default": {
                "url": "https://i.ytimg.com/vi/T7IXKQzmpK4/default.jpg",
                "width": 120,
                "height": 90
            },
            "medium": {
                "url": "https://i.ytimg.com/vi/T7IXKQzmpK4/mqdefault.jpg",
                "width": 320,
                "height": 180
            },
            "high": {
                "url": "https://i.ytimg.com/vi/T7IXKQzmpK4/hqdefault.jpg",
                "width": 480,
                "height": 360
            }
        },
        "song_lang": "",
        "vocal": "U",
        "artist": "Steve Aoki,몬스타엑스",
        "tag": ""
    },
    {
        "playlist_id": 72,
        "source": "youtube",
        "video_id": "YEWJ3E50pC4",
        "song_title": "What I Like About You",
        "thumbnails": {
            "default": {
                "url": "https://i.ytimg.com/vi/YEWJ3E50pC4/default.jpg",
                "width": 120,
                "height": 90
            },
            "medium": {
                "url": "https://i.ytimg.com/vi/YEWJ3E50pC4/mqdefault.jpg",
                "width": 320,
                "height": 180
            },
            "high": {
                "url": "https://i.ytimg.com/vi/YEWJ3E50pC4/hqdefault.jpg",
                "width": 480,
                "height": 360
            }
        },
        "song_lang": "",
        "vocal": "U",
        "artist": "Jonas Blue,Theresa Rex",
        "tag": ""
    },
    {
        "playlist_id": 72,
        "source": "youtube",
        "video_id": "o4vbu9swg4o",
        "song_title": "all the good girls go to hell",
        "thumbnails": {
            "default": {
                "url": "https://i.ytimg.com/vi/o4vbu9swg4o/default.jpg",
                "width": 120,
                "height": 90
            },
            "medium": {
                "url": "https://i.ytimg.com/vi/o4vbu9swg4o/mqdefault.jpg",
                "width": 320,
                "height": 180
            },
            "high": {
                "url": "https://i.ytimg.com/vi/o4vbu9swg4o/hqdefault.jpg",
                "width": 480,
                "height": 360
            }
        },
        "song_lang": "",
        "vocal": "U",
        "artist": "Billie Eilish",
        "tag": ""
    },
    {
        "playlist_id": 72,
        "source": "youtube",
        "video_id": "C7nj4w9Ee28",
        "song_title": "No New Friends",
        "thumbnails": {
            "default": {
                "url": "https://i.ytimg.com/vi/C7nj4w9Ee28/default.jpg",
                "width": 120,
                "height": 90
            },
            "medium": {
                "url": "https://i.ytimg.com/vi/C7nj4w9Ee28/mqdefault.jpg",
                "width": 320,
                "height": 180
            },
            "high": {
                "url": "https://i.ytimg.com/vi/C7nj4w9Ee28/hqdefault.jpg",
                "width": 480,
                "height": 360
            }
        },
        "song_lang": "",
        "vocal": "U",
        "artist": "LSD,Sia,Diplo,Labrinth",
        "tag": ""
    },
    {
        "playlist_id": 72,
        "source": "youtube",
        "video_id": "w74O60CUuhY",
        "song_title": "Can't Get Enough",
        "thumbnails": {
            "default": {
                "url": "https://i.ytimg.com/vi/w74O60CUuhY/default.jpg",
                "width": 120,
                "height": 90
            },
            "medium": {
                "url": "https://i.ytimg.com/vi/w74O60CUuhY/mqdefault.jpg",
                "width": 320,
                "height": 180
            },
            "high": {
                "url": "https://i.ytimg.com/vi/w74O60CUuhY/hqdefault.jpg",
                "width": 480,
                "height": 360
            }
        },
        "song_lang": "",
        "vocal": "U",
        "artist": "Tiësto,Mesto",
        "tag": ""
    },
    {
        "playlist_id": 72,
        "source": "youtube",
        "video_id": "XUUKW3kGHug",
        "song_title": "Rise",
        "thumbnails": {
            "default": {
                "url": "https://i.ytimg.com/vi/XUUKW3kGHug/default.jpg",
                "width": 120,
                "height": 90
            },
            "medium": {
                "url": "https://i.ytimg.com/vi/XUUKW3kGHug/mqdefault.jpg",
                "width": 320,
                "height": 180
            },
            "high": {
                "url": "https://i.ytimg.com/vi/XUUKW3kGHug/hqdefault.jpg",
                "width": 480,
                "height": 360
            }
        },
        "song_lang": "",
        "vocal": "U",
        "artist": "Jonas Blue,IZ*ONE",
        "tag": ""
    },
    {
        "playlist_id": 72,
        "source": "youtube",
        "video_id": "xoyXaJ786kE",
        "song_title": "No Sleep",
        "thumbnails": {
            "default": {
                "url": "https://i.ytimg.com/vi/xoyXaJ786kE/default.jpg",
                "width": 120,
                "height": 90
            },
            "medium": {
                "url": "https://i.ytimg.com/vi/xoyXaJ786kE/mqdefault.jpg",
                "width": 320,
                "height": 180
            },
            "high": {
                "url": "https://i.ytimg.com/vi/xoyXaJ786kE/hqdefault.jpg",
                "width": 480,
                "height": 360
            }
        },
        "song_lang": "",
        "vocal": "U",
        "artist": "Martin Garrix,Bonn",
        "tag": ""
    },
    {
        "playlist_id": 72,
        "source": "youtube",
        "video_id": "sHSYs_pojQs",
        "song_title": "bury a friend",
        "thumbnails": {
            "default": {
                "url": "https://i.ytimg.com/vi/sHSYs_pojQs/default.jpg",
                "width": 120,
                "height": 90
            },
            "medium": {
                "url": "https://i.ytimg.com/vi/sHSYs_pojQs/mqdefault.jpg",
                "width": 320,
                "height": 180
            },
            "high": {
                "url": "https://i.ytimg.com/vi/sHSYs_pojQs/hqdefault.jpg",
                "width": 480,
                "height": 360
            }
        },
        "song_lang": "",
        "vocal": "U",
        "artist": "Billie Eilish",
        "tag": ""
    },
    {
        "playlist_id": 72,
        "source": "youtube",
        "video_id": "Tztc73r8348",
        "song_title": "I Can't Get Enough",
        "thumbnails": {
            "default": {
                "url": "https://i.ytimg.com/vi/Tztc73r8348/default.jpg",
                "width": 120,
                "height": 90
            },
            "medium": {
                "url": "https://i.ytimg.com/vi/Tztc73r8348/mqdefault.jpg",
                "width": 320,
                "height": 180
            },
            "high": {
                "url": "https://i.ytimg.com/vi/Tztc73r8348/hqdefault.jpg",
                "width": 480,
                "height": 360
            }
        },
        "song_lang": "",
        "vocal": "U",
        "artist": "Benny Blanco,Tainy,Selena Gomez,J Balvin",
        "tag": ""
    },
    {
        "playlist_id": 72,
        "source": "youtube",
        "video_id": "Z6X7YdaE8Fc",
        "song_title": "Swan Song",
        "thumbnails": {
            "default": {
                "url": "https://i.ytimg.com/vi/Z6X7YdaE8Fc/default.jpg",
                "width": 120,
                "height": 90
            },
            "medium": {
                "url": "https://i.ytimg.com/vi/Z6X7YdaE8Fc/mqdefault.jpg",
                "width": 320,
                "height": 180
            },
            "high": {
                "url": "https://i.ytimg.com/vi/Z6X7YdaE8Fc/hqdefault.jpg",
                "width": 480,
                "height": 360
            }
        },
        "song_lang": "",
        "vocal": "U",
        "artist": "Dua Lipa",
        "tag": ""
    },
    {
        "playlist_id": 72,
        "source": "youtube",
        "video_id": "xwIKpc7chs0",
        "song_title": "Caught In The Fire (Explicit)",
        "thumbnails": {
            "default": {
                "url": "https://i.ytimg.com/vi/xwIKpc7chs0/default.jpg",
                "width": 120,
                "height": 90
            },
            "medium": {
                "url": "https://i.ytimg.com/vi/xwIKpc7chs0/mqdefault.jpg",
                "width": 320,
                "height": 180
            },
            "high": {
                "url": "https://i.ytimg.com/vi/xwIKpc7chs0/hqdefault.jpg",
                "width": 480,
                "height": 360
            }
        },
        "song_lang": "",
        "vocal": "U",
        "artist": "Bazzi",
        "tag": ""
    },
    {
        "playlist_id": 72,
        "source": "youtube",
        "video_id": "LTNH7PHyMRc",
        "song_title": "Last Hurrah (Acoustic)",
        "thumbnails": {
            "default": {
                "url": "https://i.ytimg.com/vi/LTNH7PHyMRc/default.jpg",
                "width": 120,
                "height": 90
            },
            "medium": {
                "url": "https://i.ytimg.com/vi/LTNH7PHyMRc/mqdefault.jpg",
                "width": 320,
                "height": 180
            },
            "high": {
                "url": "https://i.ytimg.com/vi/LTNH7PHyMRc/hqdefault.jpg",
                "width": 480,
                "height": 360
            }
        },
        "song_lang": "",
        "vocal": "U",
        "artist": "Bebe Rexha",
        "tag": ""
    },
    {
        "playlist_id": 72,
        "source": "youtube",
        "video_id": "ub6JTGwG-2I",
        "song_title": "Hello My Love",
        "thumbnails": {
            "default": {
                "url": "https://i.ytimg.com/vi/ub6JTGwG-2I/default.jpg",
                "width": 120,
                "height": 90
            },
            "medium": {
                "url": "https://i.ytimg.com/vi/ub6JTGwG-2I/mqdefault.jpg",
                "width": 320,
                "height": 180
            },
            "high": {
                "url": "https://i.ytimg.com/vi/ub6JTGwG-2I/hqdefault.jpg",
                "width": 480,
                "height": 360
            }
        },
        "song_lang": "",
        "vocal": "U",
        "artist": "Westlife",
        "tag": ""
    },
    {
        "playlist_id": 72,
        "source": "youtube",
        "video_id": "GXj0bw_iNag",
        "song_title": "West Coast (Explicit)",
        "thumbnails": {
            "default": {
                "url": "https://i.ytimg.com/vi/GXj0bw_iNag/default.jpg",
                "width": 120,
                "height": 90
            },
            "medium": {
                "url": "https://i.ytimg.com/vi/GXj0bw_iNag/mqdefault.jpg",
                "width": 320,
                "height": 180
            },
            "high": {
                "url": "https://i.ytimg.com/vi/GXj0bw_iNag/hqdefault.jpg",
                "width": 480,
                "height": 360
            }
        },
        "song_lang": "",
        "vocal": "U",
        "artist": "ALLBLACK,G-Eazy,YG,Blueface",
        "tag": ""
    },
    {
        "playlist_id": 72,
        "source": "youtube",
        "video_id": "DSoqC6ERnYA",
        "song_title": "123456",
        "thumbnails": {
            "default": {
                "url": "https://i.ytimg.com/vi/DSoqC6ERnYA/default.jpg",
                "width": 120,
                "height": 90
            },
            "medium": {
                "url": "https://i.ytimg.com/vi/DSoqC6ERnYA/mqdefault.jpg",
                "width": 320,
                "height": 180
            },
            "high": {
                "url": "https://i.ytimg.com/vi/DSoqC6ERnYA/hqdefault.jpg",
                "width": 480,
                "height": 360
            }
        },
        "song_lang": "",
        "vocal": "U",
        "artist": "Fitz and The Tantrums",
        "tag": ""
    },
    {
        "playlist_id": 72,
        "source": "youtube",
        "video_id": "Zi7Amv5zqYM",
        "song_title": "xanny",
        "thumbnails": {
            "default": {
                "url": "https://i.ytimg.com/vi/Zi7Amv5zqYM/default.jpg",
                "width": 120,
                "height": 90
            },
            "medium": {
                "url": "https://i.ytimg.com/vi/Zi7Amv5zqYM/mqdefault.jpg",
                "width": 320,
                "height": 180
            },
            "high": {
                "url": "https://i.ytimg.com/vi/Zi7Amv5zqYM/hqdefault.jpg",
                "width": 480,
                "height": 360
            }
        },
        "song_lang": "",
        "vocal": "U",
        "artist": "Billie Eilish",
        "tag": ""
    },
    {
        "playlist_id": 72,
        "source": "youtube",
        "video_id": "SpNn32HA0SI",
        "song_title": "shut up",
        "thumbnails": {
            "default": {
                "url": "https://i.ytimg.com/vi/SpNn32HA0SI/default.jpg",
                "width": 120,
                "height": 90
            },
            "medium": {
                "url": "https://i.ytimg.com/vi/SpNn32HA0SI/mqdefault.jpg",
                "width": 320,
                "height": 180
            },
            "high": {
                "url": "https://i.ytimg.com/vi/SpNn32HA0SI/hqdefault.jpg",
                "width": 480,
                "height": 360
            }
        },
        "song_lang": "",
        "vocal": "U",
        "artist": "Greyson Chance",
        "tag": ""
    },
    {
        "playlist_id": 72,
        "source": "youtube",
        "video_id": "V6FWy-sR60E",
        "song_title": "365 (Jonas Aden Remix)",
        "thumbnails": {
            "default": {
                "url": "https://i.ytimg.com/vi/V6FWy-sR60E/default.jpg",
                "width": 120,
                "height": 90
            },
            "medium": {
                "url": "https://i.ytimg.com/vi/V6FWy-sR60E/mqdefault.jpg",
                "width": 320,
                "height": 180
            },
            "high": {
                "url": "https://i.ytimg.com/vi/V6FWy-sR60E/hqdefault.jpg",
                "width": 480,
                "height": 360
            }
        },
        "song_lang": "",
        "vocal": "U",
        "artist": "Zedd,Katy Perry",
        "tag": ""
    },
    {
        "playlist_id": 72,
        "source": "youtube",
        "video_id": "tAlHa7Jevv8",
        "song_title": "Baby Mine",
        "thumbnails": {
            "default": {
                "url": "https://i.ytimg.com/vi/tAlHa7Jevv8/default.jpg",
                "width": 120,
                "height": 90
            },
            "medium": {
                "url": "https://i.ytimg.com/vi/tAlHa7Jevv8/mqdefault.jpg",
                "width": 320,
                "height": 180
            },
            "high": {
                "url": "https://i.ytimg.com/vi/tAlHa7Jevv8/hqdefault.jpg",
                "width": 480,
                "height": 360
            }
        },
        "song_lang": "",
        "vocal": "U",
        "artist": "Arcade Fire",
        "tag": ""
    },
    {
        "playlist_id": 72,
        "source": "youtube",
        "video_id": "Fva7owijgmo",
        "song_title": "8",
        "thumbnails": {
            "default": {
                "url": "https://i.ytimg.com/vi/Fva7owijgmo/default.jpg",
                "width": 120,
                "height": 90
            },
            "medium": {
                "url": "https://i.ytimg.com/vi/Fva7owijgmo/mqdefault.jpg",
                "width": 320,
                "height": 180
            },
            "high": {
                "url": "https://i.ytimg.com/vi/Fva7owijgmo/hqdefault.jpg",
                "width": 480,
                "height": 360
            }
        },
        "song_lang": "",
        "vocal": "U",
        "artist": "Billie Eilish",
        "tag": ""
    },
    {
        "playlist_id": 72,
        "source": "youtube",
        "video_id": "bVE8bfcLW3Y",
        "song_title": "my strange addiction",
        "thumbnails": {
            "default": {
                "url": "https://i.ytimg.com/vi/bVE8bfcLW3Y/default.jpg",
                "width": 120,
                "height": 90
            },
            "medium": {
                "url": "https://i.ytimg.com/vi/bVE8bfcLW3Y/mqdefault.jpg",
                "width": 320,
                "height": 180
            },
            "high": {
                "url": "https://i.ytimg.com/vi/bVE8bfcLW3Y/hqdefault.jpg",
                "width": 480,
                "height": 360
            }
        },
        "song_lang": "",
        "vocal": "U",
        "artist": "Billie Eilish",
        "tag": ""
    },
    {
        "playlist_id": 72,
        "source": "youtube",
        "video_id": "6dGgK54Bhic",
        "song_title": "ilomilo",
        "thumbnails": {
            "default": {
                "url": "https://i.ytimg.com/vi/6dGgK54Bhic/default.jpg",
                "width": 120,
                "height": 90
            },
            "medium": {
                "url": "https://i.ytimg.com/vi/6dGgK54Bhic/mqdefault.jpg",
                "width": 320,
                "height": 180
            },
            "high": {
                "url": "https://i.ytimg.com/vi/6dGgK54Bhic/hqdefault.jpg",
                "width": 480,
                "height": 360
            }
        },
        "song_lang": "",
        "vocal": "U",
        "artist": "Billie Eilish",
        "tag": ""
    },
    {
        "playlist_id": 72,
        "source": "youtube",
        "video_id": "p7bfOZek9t4",
        "song_title": "Con Altura",
        "thumbnails": {
            "default": {
                "url": "https://i.ytimg.com/vi/p7bfOZek9t4/default.jpg",
                "width": 120,
                "height": 90
            },
            "medium": {
                "url": "https://i.ytimg.com/vi/p7bfOZek9t4/mqdefault.jpg",
                "width": 320,
                "height": 180
            },
            "high": {
                "url": "https://i.ytimg.com/vi/p7bfOZek9t4/hqdefault.jpg",
                "width": 480,
                "height": 360
            }
        },
        "song_lang": "",
        "vocal": "U",
        "artist": "Rosalia,J Balvin,El Guincho",
        "tag": ""
    },
    {
        "playlist_id": 72,
        "source": "youtube",
        "video_id": "IzCz9mPBTo0",
        "song_title": "I'm Not Sorry ((Explicit))",
        "thumbnails": {
            "default": {
                "url": "https://i.ytimg.com/vi/IzCz9mPBTo0/default.jpg",
                "width": 120,
                "height": 90
            },
            "medium": {
                "url": "https://i.ytimg.com/vi/IzCz9mPBTo0/mqdefault.jpg",
                "width": 320,
                "height": 180
            },
            "high": {
                "url": "https://i.ytimg.com/vi/IzCz9mPBTo0/hqdefault.jpg",
                "width": 480,
                "height": 360
            }
        },
        "song_lang": "",
        "vocal": "U",
        "artist": "Hardwell,Mike Williams",
        "tag": ""
    },
    {
        "playlist_id": 72,
        "source": "youtube",
        "video_id": "UXfh63M5yLo",
        "song_title": "i love you",
        "thumbnails": {
            "default": {
                "url": "https://i.ytimg.com/vi/UXfh63M5yLo/default.jpg",
                "width": 120,
                "height": 90
            },
            "medium": {
                "url": "https://i.ytimg.com/vi/UXfh63M5yLo/mqdefault.jpg",
                "width": 320,
                "height": 180
            },
            "high": {
                "url": "https://i.ytimg.com/vi/UXfh63M5yLo/hqdefault.jpg",
                "width": 480,
                "height": 360
            }
        },
        "song_lang": "",
        "vocal": "U",
        "artist": "Billie Eilish",
        "tag": ""
    },
    {
        "playlist_id": 72,
        "source": "youtube",
        "video_id": "PpkcvUIzNjg",
        "song_title": "Bohemian Trapsody (Explicit)",
        "thumbnails": {
            "default": {
                "url": "https://i.ytimg.com/vi/PpkcvUIzNjg/default.jpg",
                "width": 120,
                "height": 90
            },
            "medium": {
                "url": "https://i.ytimg.com/vi/PpkcvUIzNjg/mqdefault.jpg",
                "width": 320,
                "height": 180
            },
            "high": {
                "url": "https://i.ytimg.com/vi/PpkcvUIzNjg/hqdefault.jpg",
                "width": 480,
                "height": 360
            }
        },
        "song_lang": "",
        "vocal": "U",
        "artist": "Logic",
        "tag": ""
    },
    {
        "playlist_id": 72,
        "source": "youtube",
        "video_id": "DfaoHJFVG0k",
        "song_title": "Two of Us",
        "thumbnails": {
            "default": {
                "url": "https://i.ytimg.com/vi/DfaoHJFVG0k/default.jpg",
                "width": 120,
                "height": 90
            },
            "medium": {
                "url": "https://i.ytimg.com/vi/DfaoHJFVG0k/mqdefault.jpg",
                "width": 320,
                "height": 180
            },
            "high": {
                "url": "https://i.ytimg.com/vi/DfaoHJFVG0k/hqdefault.jpg",
                "width": 480,
                "height": 360
            }
        },
        "song_lang": "",
        "vocal": "U",
        "artist": "Louis Tomlinson",
        "tag": ""
    },
    {
        "playlist_id": 72,
        "source": "youtube",
        "video_id": "WrcN9m4tgFQ",
        "song_title": "yours",
        "thumbnails": {
            "default": {
                "url": "https://i.ytimg.com/vi/WrcN9m4tgFQ/default.jpg",
                "width": 120,
                "height": 90
            },
            "medium": {
                "url": "https://i.ytimg.com/vi/WrcN9m4tgFQ/mqdefault.jpg",
                "width": 320,
                "height": 180
            },
            "high": {
                "url": "https://i.ytimg.com/vi/WrcN9m4tgFQ/hqdefault.jpg",
                "width": 480,
                "height": 360
            }
        },
        "song_lang": "",
        "vocal": "U",
        "artist": "Greyson Chance",
        "tag": ""
    },
    {
        "playlist_id": 72,
        "source": "youtube",
        "video_id": "afzsAQE19is",
        "song_title": "7 rings (Remix|Explicit)",
        "thumbnails": {
            "default": {
                "url": "https://i.ytimg.com/vi/afzsAQE19is/default.jpg",
                "width": 120,
                "height": 90
            },
            "medium": {
                "url": "https://i.ytimg.com/vi/afzsAQE19is/mqdefault.jpg",
                "width": 320,
                "height": 180
            },
            "high": {
                "url": "https://i.ytimg.com/vi/afzsAQE19is/hqdefault.jpg",
                "width": 480,
                "height": 360
            }
        },
        "song_lang": "",
        "vocal": "U",
        "artist": "Ariana Grande,2 Chainz",
        "tag": ""
    }
]